{
    "frontend":  {
       "baseURL": "/"
    },
    "routing": {
        "root": {
            "route": "/team",
            "name": "Root"
        },
        "signin": {
            "route": "/signin",
            "name": "Team Login"
        },
        "logout": {
            "route": "/logout"
        },
        "home": {
            "route": "/",
            "name": "Teamh Home"
        },
        "game": {
            "player": {
                "viewplayer": {
                    "route": "/player/view",
                    "name": "View Player"
                }
            },
            "vehicle": {
                "viewvehicle": {
                    "route": "/vehicle/view",
                    "name": "View Vehicle"
                }
            },
            "forum": {
                "viewforum": {
                    "route": "/forum/view",
                    "name": "View Forum"
                }
            }
        }
    }
}